{
  "id": "hatch-20260625",
  "name": "hatch",
  "nameZh": "hatch（哈奇）",
  "nameEn": "hatch",
  "url": "",
  "tagline": "Hatch into the light.",
  "taglineZh": "Hatch into the light.",
  "taglineEn": "",
  "category": "Lifestyle · Wellness · Incubation Brand",
  "categoryZh": "Lifestyle · Wellness · Incubation Brand",
  "categoryEn": "",
  "country": "United States",
  "countryZh": "United States",
  "countryEn": "",
  "year": 2024,
  "summary": "hatch 是一个围绕“破壳新生”概念构建的现代生活方式品牌。它以温暖米白与鼠尾草绿为主色，圆润字体与柔和摄影贯穿全触点，在理性极简与感性陪伴之间寻找平衡，目标是成为都市青年日常成长中安静而可靠的陪伴者。",
  "summaryEn": "",
  "primaryColors": [
    "#F5EFE4",
    "#A8B89C",
    "#E8A598",
    "#F4D58D",
    "#2C3E50"
  ],
  "palette": [
    {
      "hex": "#F5EFE4",
      "name": "晨曦米白",
      "nameEn": "Dawn Cream"
    },
    {
      "hex": "#A8B89C",
      "name": "鼠尾草绿",
      "nameEn": "Sage Green"
    },
    {
      "hex": "#E8A598",
      "name": "暖珊瑚",
      "nameEn": "Warm Coral"
    },
    {
      "hex": "#F4D58D",
      "name": "破壳暖黄",
      "nameEn": "Hatch Yellow"
    },
    {
      "hex": "#2C3E50",
      "name": "深岩蓝",
      "nameEn": "Deep Slate"
    }
  ],
  "logo": {
    "type": "Wordmark",
    "typeZh": "文字标识（Wordmark）",
    "description": "全小写无衬线字标“hatch”，字怀留白克制，字母 a 顶部开口呼应破壳意象。",
    "descriptionEn": "A fully lowercase sans-serif wordmark 'hatch' with restrained counters; the open top of the 'a' echoes a hatching shell.",
    "construction": "基于单圆弧与垂直笔画构建，x-height 偏大提升屏幕可读性，字母 a 采用双层结构保留呼吸感。",
    "constructionEn": "Built on a single arc and vertical strokes; an oversized x-height boosts screen legibility, and a double-storey 'a' preserves breathing room."
  },
  "typography": {
    "heading": "圆润无衬线：Nunito Rounded / Quicksand",
    "headingEn": "Nunito Rounded / Quicksand",
    "body": "现代无衬线：Inter / 思源黑体（Noto Sans SC）",
    "bodyEn": "Inter / Noto Sans SC",
    "notes": "字重控制在 Regular 与 Bold 两级，避免使用斜体；行高 1.6-1.75 保证长文可读性。",
    "notesEn": "Stick to Regular and Bold weights; avoid italics; set line-height between 1.6 and 1.75 to ensure long-form readability."
  },
  "photography": {
    "style": "自然纪实柔光风格",
    "styleEn": "Natural documentary with soft light",
    "lighting": "侧逆光模拟破晓或清晨窗光，避免硬阴影与高对比",
    "lightingEn": "Side backlight simulating dawn or morning window light; avoid hard shadows and high contrast",
    "tone": "暖米白基调，肤色柔和不饱和，整体低对比",
    "toneEn": "Warm cream undertone; soft, desaturated skin tones; overall low contrast",
    "composition": "大量留白 + 微距特写，主体居中或偏左三分之一",
    "compositionEn": "Generous negative space + macro close-ups; subjects centered or on the left-third rule"
  },
  "tone": [
    "温暖",
    "柔和",
    "现代",
    "亲切",
    "乐观",
    "克制"
  ],
  "toneEn": [],
  "toneSummary": "以“破壳”这一情感隐喻为内核，在现代极简框架中注入柔和生命力，整体氛围低饱和、低噪音、有人情味。",
  "toneSummaryEn": "",
  "positioning": "面向都市年轻人的孵化型生活方式品牌：以“破壳”为核心隐喻，把科技工具与情绪温度结合，帮助用户在日常缝隙中发现自我成长的微小瞬间。",
  "positioningEn": "",
  "targetUser": {
    "age": "25-35",
    "ageZh": "25-35 岁",
    "identity": "Urban young creators and early-career professionals seeking quiet self-growth",
    "identityZh": "寻求安静自我成长的都市青年创作者与早期职场人",
    "pain": "渴望成长却害怕改变，希望被温柔陪伴而非被催促",
    "painZh": "想要成长又怕改变，渴望被温柔陪伴而非被催促",
    "scene": "Morning commute, midday solitude, and evening journaling",
    "sceneZh": "晨间通勤、午休独处、晚间复盘"
  },
  "targetUserEn": null,
  "sellingPoints": [
    "以“破壳新生”为情感锚点，区别于冷感的纯科技品牌。",
    "全小写无衬线 logo 强化亲切感与互联网原生基因。",
    "米白 + 鼠尾草绿主色构建自然疗愈的视觉氛围。",
    "圆润字体与柔光摄影贯穿所有触点，降低决策门槛。",
    "暖黄仅作关键行动点点缀，引导转化而不打扰。"
  ],
  "sellingPointsEn": [],
  "brandTakeaway": [],
  "brandTakeawayEn": [],
  "radar": {
    "克制": 6.5,
    "温度感": 9,
    "游戏化": 2,
    "科技感": 5,
    "情感连接": 9,
    "识别强度": 7.5
  },
  "heuristicRadar": null,
  "heuristicRadarArray": null,
  "heuristicDetail": null,
  "meta": {
    "favicon": "",
    "ogImage": "",
    "heroImage": "",
    "logoCandidates": []
  },
  "reportFile": "brands/hatch-20260625.json",
  "reportUrl": "/report/hatch-20260625",
  "createdAt": "2026-06-25"
}
